essay_wechat_analysis_mcp_server_lc/__init__.py
essay_wechat_analysis_mcp_server_lc/server.py
essay_wechat_analysis_mcp_server_lc-0.2.0.dist-info/WHEEL
essay_wechat_analysis_mcp_server_lc-0.2.0.dist-info/entry_points.txt
essay_wechat_analysis_mcp_server_lc-0.2.0.dist-info/METADATA
essay_wechat_analysis_mcp_server_lc-0.2.0.dist-info/RECORD
