Metadata-Version: 2.3
Name: essay-wechat-analysis-mcp-server-lc
Version: 0.2.0
Summary: Add your description here
Author: Melle_lichao
Author-email: Melle_lichao <lichao10060909@163.com>
Requires-Dist: aiomysql>=0.3.2
Requires-Dist: mcp[cli]>=1.21.0
Requires-Python: >=3.12
